pyutils_pkg/__init__.py
pyutils_pkg-0.1.0.dist-info/LICENSE
pyutils_pkg-0.1.0.dist-info/METADATA
pyutils_pkg-0.1.0.dist-info/WHEEL
pyutils_pkg-0.1.0.dist-info/RECORD
