Metadata-Version: 2.1
Name: pyutils-pkg
Version: 0.1.0
Summary: PyUtils Package
Author: Mustafa Elghrib
Author-email: mustafaelghriib@gmail.com
Requires-Python: >=3.11,<4.0
Classifier: License :: OSI Approved :: MIT License
Classifier: Operating System :: OS Independent
Classifier: Programming Language :: Python :: 3
Classifier: Programming Language :: Python :: 3.11
